{
  "checks": {
    "status": 200,
    "url": "https://app.eycvector.com/admin/strategies",
    "hasStrategyLanes": true,
    "redFailureTerms": 9,
    "hasOwnerReview": true,
    "hasNextAction": false,
    "hasOwner": true,
    "pageErrors": 0,
    "consoleErrorCount": 0
  },
  "textSample": "I\nIUF · 戰情台\nv3.0 · TACTICAL\n台股 AI 交易戰情室\n操作員 · IUF-01\n模擬模式 / 風控守門\n戰情台\n盤勢與任務\n市場情報\n重大訊息\nAI 推薦\n推薦引擎\n交易室\n委託與部位\n公司 / 主題\n公司圖譜\n量化策略\nSIM-only\nOPENALICE\nBrain\nLLM 費用\nEventLog\n事件流\nPortfolio\n快照版本\nTools\n工具登錄\nUTA\n帳號管理\nStrategies\nLab 策略狀態\nMARKET · INTEL\n正式資料 / 風控守門\n登出\n警示通知，無未讀\nQuant Lab — Strategy Lanes\nGround truth: Codex S1 state 2026-05-18 11:29 TST  ·  Owner-only\nQuant Lab 目前僅推進 S1。S1 owner-review packet 已建置完畢，Bruce 10/10 attest PASS， 但所有 broker / order / capital permissions 仍為 false，尚未取得楊董 review。 Old cont_liq v36 top4 仍獨立追蹤並 C04 FAIL。Class5 v3/v4 為 phantom / research-paused， 任何來自 5/15 MEMORY 的描述均不可引用為已驗證 shipped evidence。\nACTIVE LANES (3)\nSTRATEGY ID\niuf_ls_omni_v1_router\nS1 iuf_ls_omni_v1_router\nOWNER-REVIEW PACKET\n品質鎖 CHECKLIST\n10/10\nLast update: 2026/5/18 11:29:00\n全部 PERMISSIONS = FALSE\n✗ broker / order\n✗ registry state\n✗ capital use\n✗ live-ready\n✗ paper-ready\n10M SIM owner-review packet — 待楊董 review\n狀態說明\nLong engine: cont_liq v36R top8\nHedge: 00632R (crisis-only, 0.60 target weight, adjusted-price verified)\nBruce attest: PACKET_ATTEST_PASS 10/10\nRoute proxy: 421 days, compound +215.91%, max drawdown -13.18%\nSoft-throttle row: 2485 on 2025-08-25 (needs split/size reduction in SIM policy)\nEVIDENCE FILES (READ-ONLY, IUF_QUANT_LAB)\nreports/data_lane/s1_iuf_ls_omni_owner_review_packet_2026_05_18_v1.json\nreports/data_lane/s1_iuf_ls_omni_owner_review_packet_attest_v1.json\nreports/data_lane/s1_iuf_ls_omni_risk_budget_10m_sim_v1.json\nreports/data_lane/s1_iuf_ls_omni_capacity_proxy_10m_sim_v1.json\nreports/data_lane/s1_intraday_partial_fill_proxy_v1.json\nreports/data_lane/s1_inverse_hedge_bakeoff_v1.json\nSTRATEGY ID\ncont_liq_v36_h20_top4_regime_pos006\ncont_liq v36 top4 (baseline)\nBASELINE — C04 FAIL\n品質鎖 CHECKLIST\n10/11\nLast update: 2026/5/18 11:29:00\n全部 PERMISSIONS = FALSE\n✗ broker / order\n✗ registry state\n✗ capital use\n✗ live-ready\n✗ paper-ready\n狀態說明\nC04 STRICT_BROAD_FAMILY_EVIDENCE_GATE FAIL: broad-family max-T p=0.09979 > threshold 0.05\nStrict statistical clearance route: NOT OPEN\nC11 owner risk budget: NOW SOLVED (10M TWD / max loss 300K TWD)\nv36 top4 is not dead, but cannot be described as fully cleared\ncont_liq v36R top8 is the long engine inside S1 — treat as S1 component only\nEVIDENCE FILES (READ-ONLY, IUF_QUANT_LAB)\nreports/data_lane/codex_cont_liq_v36_capital_test_preflight_v1.json\nSTRATEGY ID\nclass5_v3_v4\nClass5 v3/v4\nRESEARCH-PAUSED\n品質鎖 CHECKLIST\n0/13\nLast update: 2026/5/18 11:29:00\n全部 PERMISSIONS = FALSE\n✗ broker / order\n✗ registry state\n✗ capital use\n✗ live-ready\n✗ paper-ready\n狀態說明\nDisk status: phantom / no source artifacts\nCurrent state: research-paused pending fresh hypothesis spec\nPHANTOM / RETRACTED CLAIMS — 不可引用\nPHANTOM\nClass5 Truth Board v15 / Class5 v3 PASS / v4 redesign\nPHANTOM\nSprint Cycle 4 cont_liq Period 2 sector cap 3 PASS\nPHANTOM\nRound-2 fixture publish under research/fixtures/\nPHANTOM\nFamily C x SBL v3 PASS\nEVIDENCE FILES (READ-ONLY, IUF_QUANT_LAB)\nreports/data_lane/athena_memory_phantom_retraction_packet_2026_05_18_v1.md\nreports/data_lane/athena_path_a_retract_draft_2026_05_18.md\n可說: \"owner-review packet exists\" / \"Bruce 10/10 attest PASS\" / \"10M SIM research packet\" / \"S1 is packaged for Yang owner review\"  \n不可說: \"capital-approved\" / \"alpha confirmed\" / \"live-ready\" / \"paper-ready\" / \"可實單\" / \"產品化完成\" / \"follow-trade\"",
  "consoleMessages": [],
  "pageErrors": []
}